{
  "number": 123456, 
  "montant": 50.00,
  "date": "2024-04-25",
  "time": "08:30:00",
   "marque": {
    "ice": "123456789",
    "nom": "Nom de la marque",
    "logo": "url_du_logo",
    "website": "url_du_site_web"
  },
  "produits": [
    {
      "reference": "REF123",
      "description": "Description du produit",
      "quantity": 1,
      "prix": 20.00,
      "ht": 16.67,
      "tva": 3.33,
      "category": {
        "type": "Type de la catégorie"
      }
    },
    {
      "reference": "REF456",
      "description": "Description du produit",
      "quantity": 2,
      "prix": 15.00,
      "ht": 12.50,
      "tva": 2.50,
      "category": {
        "type": "Type de la catégorie"
      }
    }
  ]
}
